target_benchmark/__init__.py
target_benchmark/dataset_loaders/AbsDatasetLoader.py
target_benchmark/dataset_loaders/DatasetLoaderEnums.py
target_benchmark/dataset_loaders/GenericDatasetLoader.py
target_benchmark/dataset_loaders/HFDatasetLoader.py
target_benchmark/dataset_loaders/LoadersDataModels.py
target_benchmark/dataset_loaders/NeedleInHaystackDataLoader.py
target_benchmark/dataset_loaders/TargetDatasetConfig.py
target_benchmark/dataset_loaders/Text2SQLDatasetLoader.py
target_benchmark/dataset_loaders/__init__.py
target_benchmark/dataset_loaders/utils.py
target_benchmark/dictionary_keys.py
target_benchmark/evaluators/TARGET.py
target_benchmark/evaluators/__init__.py
target_benchmark/evaluators/utils.py
target_benchmark/generators/AbsGenerator.py
target_benchmark/generators/DefaultGenerator.py
target_benchmark/generators/GeneratorPrompts.py
target_benchmark/generators/GeneratorsDataModels.py
target_benchmark/generators/Text2SQLGenerator.py
target_benchmark/generators/__init__.py
target_benchmark/retrievers/AbsCustomEmbeddingRetriever.py
target_benchmark/retrievers/AbsRetrieverBase.py
target_benchmark/retrievers/AbsStandardEmbeddingRetriever.py
target_benchmark/retrievers/RetrieversDataModels.py
target_benchmark/retrievers/__init__.py
target_benchmark/retrievers/analysis/NoContextRetriever.py
target_benchmark/retrievers/analysis/__init__.py
target_benchmark/retrievers/context/NoContextRetriever.py
target_benchmark/retrievers/context/__init__.py
target_benchmark/retrievers/hyse/HySERetriever.py
target_benchmark/retrievers/hyse/__init__.py
target_benchmark/retrievers/llama_index/LlamaIndexRetriever.py
target_benchmark/retrievers/llama_index/__init__.py
target_benchmark/retrievers/llama_index/embedding_utils.py
target_benchmark/retrievers/naive/DefaultOpenAIEmbeddingRetriever.py
target_benchmark/retrievers/naive/HNSWOpenAIEmbeddingRetriever.py
target_benchmark/retrievers/naive/T5EmbeddingRetriever.py
target_benchmark/retrievers/naive/__init__.py
target_benchmark-0.1.3.dist-info/LICENSE
target_benchmark-0.1.3.dist-info/METADATA
target_benchmark-0.1.3.dist-info/WHEEL
target_benchmark-0.1.3.dist-info/RECORD
