Metadata-Version: 2.3
Name: target_benchmark
Version: 0.1.3
Summary: Table Retrieval for Generative Tasks Benchmark
License: Apache-2.0
Author: Xingyu Ji
Author-email: jixy2012@berkeley.edu
Requires-Python: >=3.9,<4.0
Classifier: License :: OSI Approved :: Apache Software License
Classifier: Operating System :: OS Independent
Classifier: Programming Language :: Python :: 3
Classifier: Programming Language :: Python :: 3.9
Classifier: Programming Language :: Python :: 3.10
Classifier: Programming Language :: Python :: 3.11
Classifier: Programming Language :: Python :: 3.12
Classifier: Programming Language :: Python :: 3.13
Provides-Extra: llamaindex-retriever
Provides-Extra: ottqa-retriever
Requires-Dist: datasets (>=2.19.0,<3.0.0)
Requires-Dist: evaluate (>=0.4.2,<0.5.0)
Requires-Dist: func-timeout (>=4.3.5,<5.0.0)
Requires-Dist: hnswlib (>=0.8.0,<0.9.0)
Requires-Dist: langchain (>=0.1.16,<0.2.0)
Requires-Dist: langchain-community (>=0.0.34,<0.0.35)
Requires-Dist: langchain-core (>=0.1.45,<0.2.0)
Requires-Dist: langchain-openai (>=0.0.8,<0.0.9)
Requires-Dist: langchain-text-splitters (>=0.0.1,<0.0.2)
Requires-Dist: llama-index (>=0.10.58,<0.11.0) ; extra == "llamaindex-retriever"
Requires-Dist: nltk (>=3.8.1,<4.0.0) ; extra == "ottqa-retriever"
Requires-Dist: numpy (>=1.26.4,<2.0.0)
Requires-Dist: pandas (>=2.2.2,<3.0.0)
Requires-Dist: pexpect (>=4.9.0,<5.0.0) ; extra == "ottqa-retriever"
Requires-Dist: pydantic (>=2.7.4,<3.0.0)
Requires-Dist: python-dateutil (>=2.9.0,<3.0.0)
Requires-Dist: python-dotenv (>=1.0.1,<2.0.0)
Requires-Dist: qdrant-client (>=1.9.1,<2.0.0)
Requires-Dist: regex (>=2023.10.3,<2024.0.0)
Requires-Dist: rouge-score (>=0.1.2,<0.2.0)
Requires-Dist: sacrebleu (>=2.4.2,<3.0.0)
Requires-Dist: scikit-learn (>=1.3.0,<2.0.0)
Requires-Dist: scipy (>=1.13.0,<2.0.0)
Requires-Dist: spacy (>=3.7.4,<4.0.0) ; extra == "ottqa-retriever"
Requires-Dist: tqdm (>=4.65.0,<5.0.0)
Requires-Dist: transformers (>=4.41.2,<5.0.0)
Project-URL: Homepage, https://target-benchmark.github.io/
Project-URL: Repository, https://github.com/target-benchmark/target
